README.md
setup.py
cyber_201_suspicious_library/__init__.py
cyber_201_suspicious_library/helper_utils.py
cyber_201_suspicious_library.egg-info/PKG-INFO
cyber_201_suspicious_library.egg-info/SOURCES.txt
cyber_201_suspicious_library.egg-info/dependency_links.txt
cyber_201_suspicious_library.egg-info/requires.txt
cyber_201_suspicious_library.egg-info/top_level.txt